{
  "success": true,
  "data": [
    { "status": "Online",  "id": 1, "lastName": "Snow", "firstName": "Jon", "age": 35  },
    { "status": "Offline",  "id": 2, "lastName": "Lannister", "firstName": "Cersei", "age": 42 },
    { "status": "Online",  "id": 3, "lastName": "Lannister", "firstName": "Jaime", "age": 45 },
    { "status": "Online",  "id": 4, "lastName": "Stark", "firstName": "Arya", "age": 16 },
    { "status": "Online",  "id": 5, "lastName": "Targaryen", "firstName": "Daenerys", "age": null },
    { "status": "Online",  "id": 6, "lastName": "Melisandre", "firstName": null, "age": 150 },
    { "status": "Online",  "id": 7, "lastName": "Clifford", "firstName": "Ferrara", "age": 44 },
    { "status": "Online",  "id": 8, "lastName": "Frances", "firstName": "Rossini", "age": 36 },
    { "status": "Online",  "id": 9, "lastName": "Roxie", "firstName": "Harvey", "age": 65 },
    { "status": "Online",  "id": 10, "lastName": "Snow", "firstName": "Jon", "age": 35 },
    { "status": "Online",  "id": 11, "lastName": "Lannister", "firstName": "Cersei", "age": 42 },
    { "status": "Online",  "id": 12, "lastName": "Lannister", "firstName": "Jaime", "age": 45 },
    { "status": "Online",  "id": 13, "lastName": "Stark", "firstName": "Arya", "age": 16 },
    { "status": "Online",  "id": 14, "lastName": "Targaryen", "firstName": "Daenerys", "age": null },
    { "status": "Online",  "id": 15, "lastName": "Melisandre", "firstName": null, "age": 150 },
    { "status": "Online",  "id": 16, "lastName": "Clifford", "firstName": "Ferrara", "age": 44 },
    { "status": "Online",  "id": 17, "lastName": "Frances", "firstName": "Rossini", "age": 36 },
    { "status": "Online",  "id": 18, "lastName": "Roxie", "firstName": "Harvey", "age": 65 },
    { "status": "Online",  "id": 19, "lastName": "Frances", "firstName": "Rossini", "age": 36 },
    { "status": "Online",  "id": 20, "lastName": "Roxie", "firstName": "Harvey", "age": 65 },
    { "status": "Online",  "id": 21, "lastName": "Lannister", "firstName": "Cersei", "age": 42 },
    { "status": "Online",  "id": 22, "lastName": "Lannister", "firstName": "Jaime", "age": 45 },
    { "status": "Online",  "id": 23, "lastName": "Stark", "firstName": "Arya", "age": 16 },
    { "status": "Online",  "id": 24, "lastName": "Targaryen", "firstName": "Daenerys", "age": null },
    { "status": "Online",  "id": 25, "lastName": "Melisandre", "firstName": null, "age": 150 },
    { "status": "Online",  "id": 26, "lastName": "Clifford", "firstName": "Ferrara", "age": 44 },
    { "status": "Online",  "id": 27, "lastName": "Frances", "firstName": "Rossini", "age": 36 },
    { "status": "Online",  "id": 28, "lastName": "Roxie", "firstName": "Harvey", "age": 65 },
    { "status": "Online",  "id": 29, "lastName": "Frances", "firstName": "Rossini", "age": 36 },
    { "status": "Online",  "id": 30, "lastName": "Roxie", "firstName": "Harvey", "age": 65 },
    { "status": "Online",  "id": 31, "lastName": "Lannister", "firstName": "Cersei", "age": 42 },
    { "status": "Online",  "id": 32, "lastName": "Lannister", "firstName": "Jaime", "age": 45 },
    { "status": "Online",  "id": 33, "lastName": "Stark", "firstName": "Arya", "age": 16 },
    { "status": "Online",  "id": 34, "lastName": "Targaryen", "firstName": "Daenerys", "age": null },
    { "status": "Online",  "id": 35, "lastName": "Melisandre", "firstName": null, "age": 150 },
    { "status": "Online",  "id": 36, "lastName": "Clifford", "firstName": "Ferrara", "age": 44 },
    { "status": "Online",  "id": 37, "lastName": "Frances", "firstName": "Rossini", "age": 36 },
    { "status": "Online",  "id": 38, "lastName": "Roxie", "firstName": "Harvey", "age": 65 },
    { "status": "Online",  "id": 39, "lastName": "Frances", "firstName": "Rossini", "age": 36 },
    { "status": "Online",  "id": 40, "lastName": "Roxie", "firstName": "Harvey", "age": 65 },
    { "status": "Online",  "id": 41, "lastName": "Lannister", "firstName": "Cersei", "age": 42 },
    { "status": "Online",  "id": 42, "lastName": "Lannister", "firstName": "Jaime", "age": 45 },
    { "status": "Online",  "id": 43, "lastName": "Stark", "firstName": "Arya", "age": 16 },
    { "status": "Online",  "id": 44, "lastName": "Targaryen", "firstName": "Daenerys", "age": null },
    { "status": "Online",  "id": 45, "lastName": "Melisandre", "firstName": null, "age": 150 },
    { "status": "Online",  "id": 46, "lastName": "Clifford", "firstName": "Ferrara", "age": 44 },
    { "status": "Online",  "id": 47, "lastName": "Frances", "firstName": "Rossini", "age": 36 },
    { "status": "Online",  "id": 48, "lastName": "Roxie", "firstName": "Harvey", "age": 65 },
    { "status": "Online",  "id": 49, "lastName": "Frances", "firstName": "Rossini", "age": 36 },
    { "status": "Online",  "id": 50, "lastName": "Roxie", "firstName": "Harvey", "age": 65 },
    { "status": "Online",  "id": 51, "lastName": "Lannister", "firstName": "Cersei", "age": 42 },
    { "status": "Online",  "id": 52, "lastName": "Lannister", "firstName": "Jaime", "age": 45 },
    { "status": "Online",  "id": 53, "lastName": "Stark", "firstName": "Arya", "age": 16 },
    { "status": "Online",  "id": 54, "lastName": "Targaryen", "firstName": "Daenerys", "age": null },
    { "status": "Online",  "id": 55, "lastName": "Melisandre", "firstName": null, "age": 150 },
    { "status": "Online",  "id": 56, "lastName": "Clifford", "firstName": "Ferrara", "age": 44 },
    { "status": "Online",  "id": 57, "lastName": "Frances", "firstName": "Rossini", "age": 36 },
    { "status": "Online",  "id": 58, "lastName": "Roxie", "firstName": "Harvey", "age": 65 },
    { "status": "Online",  "id": 59, "lastName": "Frances", "firstName": "Rossini", "age": 36 },
    { "status": "Online",  "id": 60, "lastName": "Roxie", "firstName": "Harvey", "age": 65 },
    { "status": "Online",  "id": 61, "lastName": "Lannister", "firstName": "Cersei", "age": 42 },
    { "status": "Online",  "id": 62, "lastName": "Lannister", "firstName": "Jaime", "age": 45 },
    { "status": "Online",  "id": 63, "lastName": "Stark", "firstName": "Arya", "age": 16 },
    { "status": "Online",  "id": 64, "lastName": "Targaryen", "firstName": "Daenerys", "age": null },
    { "status": "Online",  "id": 65, "lastName": "Melisandre", "firstName": null, "age": 150 },
    { "status": "Online",  "id": 66, "lastName": "Clifford", "firstName": "Ferrara", "age": 44 },
    { "status": "Online",  "id": 67, "lastName": "Frances", "firstName": "Rossini", "age": 36 },
    { "status": "Online",  "id": 68, "lastName": "Roxie", "firstName": "Harvey", "age": 65 },
    { "status": "Online",  "id": 69, "lastName": "Frances", "firstName": "Rossini", "age": 36 },
    { "status": "Online",  "id": 70, "lastName": "Roxie", "firstName": "Harvey", "age": 65 },
    { "status": "Online",  "id": 71, "lastName": "Lannister", "firstName": "Cersei", "age": 42 },
    { "status": "Online",  "id": 72, "lastName": "Lannister", "firstName": "Jaime", "age": 45 },
    { "status": "Online",  "id": 73, "lastName": "Stark", "firstName": "Arya", "age": 16 },
    { "status": "Online",  "id": 74, "lastName": "Targaryen", "firstName": "Daenerys", "age": null },
    { "status": "Online",  "id": 75, "lastName": "Melisandre", "firstName": null, "age": 150 },
    { "status": "Online",  "id": 76, "lastName": "Clifford", "firstName": "Ferrara", "age": 44 },
    { "status": "Online",  "id": 77, "lastName": "Frances", "firstName": "Rossini", "age": 36 },
    { "status": "Online",  "id": 78, "lastName": "Roxie", "firstName": "Harvey", "age": 65 },
    { "status": "Online",  "id": 79, "lastName": "Frances", "firstName": "Rossini", "age": 36 },
    { "status": "Online",  "id": 80, "lastName": "Roxie", "firstName": "Harvey", "age": 65 },
    { "status": "Online",  "id": 81, "lastName": "Lannister", "firstName": "Cersei", "age": 42 },
    { "status": "Online",  "id": 82, "lastName": "Lannister", "firstName": "Jaime", "age": 45 },
    { "status": "Online",  "id": 83, "lastName": "Stark", "firstName": "Arya", "age": 16 },
    { "status": "Online",  "id": 84, "lastName": "Targaryen", "firstName": "Daenerys", "age": null },
    { "status": "Online",  "id": 85, "lastName": "Melisandre", "firstName": null, "age": 150 },
    { "status": "Online",  "id": 86, "lastName": "Clifford", "firstName": "Ferrara", "age": 44 },
    { "status": "Online",  "id": 87, "lastName": "Frances", "firstName": "Rossini", "age": 36 },
    { "status": "Online",  "id": 88, "lastName": "Roxie", "firstName": "Harvey", "age": 65 },
    { "status": "Online",  "id": 89, "lastName": "Frances", "firstName": "Rossini", "age": 36 },
    { "status": "Online",  "id": 90, "lastName": "Roxie", "firstName": "Harvey", "age": 65 },
    { "status": "Online",  "id": 91, "lastName": "Lannister", "firstName": "Cersei", "age": 42 },
    { "status": "Online",  "id": 92, "lastName": "Lannister", "firstName": "Jaime", "age": 45 },
    { "status": "Online",  "id": 93, "lastName": "Stark", "firstName": "Arya", "age": 16 },
    { "status": "Online",  "id": 94, "lastName": "Targaryen", "firstName": "Daenerys", "age": null },
    { "status": "Online",  "id": 95, "lastName": "Melisandre", "firstName": null, "age": 150 },
    { "status": "Online",  "id": 96, "lastName": "Clifford", "firstName": "Ferrara", "age": 44 },
    { "status": "Online",  "id": 97, "lastName": "Frances", "firstName": "Rossini", "age": 36 },
    { "status": "Online",  "id": 98, "lastName": "Roxie", "firstName": "Harvey", "age": 65 },
    { "status": "Online",  "id": 99, "lastName": "Frances", "firstName": "Rossini", "age": 36 },
    { "status": "Online",  "id": 100, "lastName": "Roxie", "firstName": "Harvey", "age": 65 },
    { "status": "Online",  "id": 101, "lastName": "Lannister", "firstName": "Cersei", "age": 42 },
    { "status": "Online",  "id": 102, "lastName": "Lannister", "firstName": "Jaime", "age": 45 },
    { "status": "Online",  "id": 103, "lastName": "Stark", "firstName": "Arya", "age": 16 },
    { "status": "Online",  "id": 104, "lastName": "Targaryen", "firstName": "Daenerys", "age": null },
    { "status": "Online",  "id": 105, "lastName": "Melisandre", "firstName": null, "age": 150 },
    { "status": "Online",  "id": 106, "lastName": "Clifford", "firstName": "Ferrara", "age": 44 },
    { "status": "Online",  "id": 107, "lastName": "Frances", "firstName": "Rossini", "age": 36 },
    { "status": "Online",  "id": 108, "lastName": "Roxie", "firstName": "Harvey", "age": 65 },
    { "status": "Online",  "id": 109, "lastName": "Frances", "firstName": "Rossini", "age": 36 },
    { "status": "Online",  "id": 110, "lastName": "Roxie", "firstName": "Harvey", "age": 65 },
    { "status": "Online",  "id": 111, "lastName": "Lannister", "firstName": "Cersei", "age": 42 },
    { "status": "Online",  "id": 112, "lastName": "Lannister", "firstName": "Jaime", "age": 45 },
    { "status": "Online",  "id": 113, "lastName": "Stark", "firstName": "Arya", "age": 16 },
    { "status": "Online",  "id": 114, "lastName": "Targaryen", "firstName": "Daenerys", "age": null },
    { "status": "Online",  "id": 115, "lastName": "Melisandre", "firstName": null, "age": 150 },
    { "status": "Online",  "id": 116, "lastName": "Clifford", "firstName": "Ferrara", "age": 44 },
    { "status": "Online",  "id": 117, "lastName": "Frances", "firstName": "Rossini", "age": 36 },
    { "status": "Online",  "id": 118, "lastName": "Roxie", "firstName": "Harvey", "age": 65 },
    { "status": "Online",  "id": 119, "lastName": "Frances", "firstName": "Rossini", "age": 36 },
    { "status": "Online",  "id": 120, "lastName": "Roxie", "firstName": "Harvey", "age": 65 },
    { "status": "Online",  "id": 121, "lastName": "Lannister", "firstName": "Cersei", "age": 42 },
    { "status": "Online",  "id": 122, "lastName": "Lannister", "firstName": "Jaime", "age": 45 },
    { "status": "Online",  "id": 123, "lastName": "Stark", "firstName": "Arya", "age": 16 },
    { "status": "Online",  "id": 124, "lastName": "Targaryen", "firstName": "Daenerys", "age": null },
    { "status": "Online",  "id": 125, "lastName": "Melisandre", "firstName": null, "age": 150 },
    { "status": "Online",  "id": 126, "lastName": "Clifford", "firstName": "Ferrara", "age": 44 },
    { "status": "Online",  "id": 127, "lastName": "Frances", "firstName": "Rossini", "age": 36 },
    { "status": "Online",  "id": 128, "lastName": "Roxie", "firstName": "Harvey", "age": 65 },
    { "status": "Online",  "id": 129, "lastName": "Frances", "firstName": "Rossini", "age": 36 },
    { "status": "Online",  "id": 130, "lastName": "Roxie", "firstName": "Harvey", "age": 65 },
    { "status": "Online",  "id": 131, "lastName": "Lannister", "firstName": "Cersei", "age": 42 },
    { "status": "Online",  "id": 132, "lastName": "Lannister", "firstName": "Jaime", "age": 45 },
    { "status": "Online",  "id": 133, "lastName": "Stark", "firstName": "Arya", "age": 16 },
    { "status": "Online",  "id": 134, "lastName": "Targaryen", "firstName": "Daenerys", "age": null },
    { "status": "Online",  "id": 135, "lastName": "Melisandre", "firstName": null, "age": 150 },
    { "status": "Online",  "id": 136, "lastName": "Clifford", "firstName": "Ferrara", "age": 44 },
    { "status": "Online",  "id": 137, "lastName": "Frances", "firstName": "Rossini", "age": 36 },
    { "status": "Online",  "id": 138, "lastName": "Roxie", "firstName": "Harvey", "age": 65 },
    { "status": "Online",  "id": 139, "lastName": "Frances", "firstName": "Rossini", "age": 36 },
    { "status": "Online",  "id": 140, "lastName": "Roxie", "firstName": "Harvey", "age": 65 },
    { "status": "Online",  "id": 141, "lastName": "Lannister", "firstName": "Cersei", "age": 42 },
    { "status": "Online",  "id": 142, "lastName": "Lannister", "firstName": "Jaime", "age": 45 },
    { "status": "Online",  "id": 143, "lastName": "Stark", "firstName": "Arya", "age": 16 },
    { "status": "Online",  "id": 144, "lastName": "Targaryen", "firstName": "Daenerys", "age": null },
    { "status": "Online",  "id": 145, "lastName": "Melisandre", "firstName": null, "age": 150 },
    { "status": "Online",  "id": 146, "lastName": "Clifford", "firstName": "Ferrara", "age": 44 },
    { "status": "Online",  "id": 147, "lastName": "Frances", "firstName": "Rossini", "age": 36 },
    { "status": "Online",  "id": 148, "lastName": "Roxie", "firstName": "Harvey", "age": 65 },
    { "status": "Online",  "id": 149, "lastName": "Frances", "firstName": "Rossini", "age": 36 },
    { "status": "Online",  "id": 150, "lastName": "Roxie", "firstName": "Harvey", "age": 65 },
    { "status": "Online",  "id": 151, "lastName": "Lannister", "firstName": "Cersei", "age": 42 },
    { "status": "Online",  "id": 152, "lastName": "Lannister", "firstName": "Jaime", "age": 45 },
    { "status": "Online",  "id": 153, "lastName": "Stark", "firstName": "Arya", "age": 16 },
    { "status": "Online",  "id": 154, "lastName": "Targaryen", "firstName": "Daenerys", "age": null },
    { "status": "Online",  "id": 155, "lastName": "Melisandre", "firstName": null, "age": 150 },
    { "status": "Online",  "id": 156, "lastName": "Clifford", "firstName": "Ferrara", "age": 44 },
    { "status": "Online",  "id": 157, "lastName": "Frances", "firstName": "Rossini", "age": 36 },
    { "status": "Online",  "id": 158, "lastName": "Roxie", "firstName": "Harvey", "age": 65 },
    { "status": "Online",  "id": 159, "lastName": "Frances", "firstName": "Rossini", "age": 36 },
    { "status": "Online",  "id": 160, "lastName": "Roxie", "firstName": "Harvey", "age": 65 },
    { "status": "Online",  "id": 161, "lastName": "Lannister", "firstName": "Cersei", "age": 42 },
    { "status": "Online",  "id": 162, "lastName": "Lannister", "firstName": "Jaime", "age": 45 },
    { "status": "Online",  "id": 163, "lastName": "Stark", "firstName": "Arya", "age": 16 },
    { "status": "Online",  "id": 164, "lastName": "Targaryen", "firstName": "Daenerys", "age": null },
    { "status": "Online",  "id": 165, "lastName": "Melisandre", "firstName": null, "age": 150 },
    { "status": "Online",  "id": 166, "lastName": "Clifford", "firstName": "Ferrara", "age": 44 },
    { "status": "Online",  "id": 167, "lastName": "Frances", "firstName": "Rossini", "age": 36 },
    { "status": "Online",  "id": 168, "lastName": "Roxie", "firstName": "Harvey", "age": 65 },
    { "status": "Online",  "id": 169, "lastName": "Frances", "firstName": "Rossini", "age": 36 },
    { "status": "Online",  "id": 170, "lastName": "Roxie", "firstName": "Harvey", "age": 65 },
    { "status": "Online",  "id": 171, "lastName": "Lannister", "firstName": "Cersei", "age": 42 },
    { "status": "Online",  "id": 172, "lastName": "Lannister", "firstName": "Jaime", "age": 45 },
    { "status": "Online",  "id": 173, "lastName": "Stark", "firstName": "Arya", "age": 16 },
    { "status": "Online",  "id": 174, "lastName": "Targaryen", "firstName": "Daenerys", "age": null },
    { "status": "Online",  "id": 175, "lastName": "Melisandre", "firstName": null, "age": 150 },
    { "status": "Online",  "id": 176, "lastName": "Clifford", "firstName": "Ferrara", "age": 44 },
    { "status": "Online",  "id": 177, "lastName": "Frances", "firstName": "Rossini", "age": 36 },
    { "status": "Online",  "id": 178, "lastName": "Roxie", "firstName": "Harvey", "age": 65 },
    { "status": "Online",  "id": 179, "lastName": "Frances", "firstName": "Rossini", "age": 36 },
    { "status": "Online",  "id": 180, "lastName": "Roxie", "firstName": "Harvey", "age": 65 },
    { "status": "Online",  "id": 181, "lastName": "Lannister", "firstName": "Cersei", "age": 42 },
    { "status": "Online",  "id": 182, "lastName": "Lannister", "firstName": "Jaime", "age": 45 },
    { "status": "Online",  "id": 183, "lastName": "Stark", "firstName": "Arya", "age": 16 },
    { "status": "Online",  "id": 184, "lastName": "Targaryen", "firstName": "Daenerys", "age": null },
    { "status": "Online",  "id": 185, "lastName": "Melisandre", "firstName": null, "age": 150 },
    { "status": "Online",  "id": 186, "lastName": "Clifford", "firstName": "Ferrara", "age": 44 },
    { "status": "Online",  "id": 187, "lastName": "Frances", "firstName": "Rossini", "age": 36 },
    { "status": "Online",  "id": 188, "lastName": "Roxie", "firstName": "Harvey", "age": 65 },
    { "status": "Online",  "id": 189, "lastName": "Frances", "firstName": "Rossini", "age": 36 },
    { "status": "Online",  "id": 190, "lastName": "Roxie", "firstName": "Harvey", "age": 65 },
    { "status": "Online",  "id": 191, "lastName": "Lannister", "firstName": "Cersei", "age": 42 },
    { "status": "Online",  "id": 192, "lastName": "Lannister", "firstName": "Jaime", "age": 45 },
    { "status": "Online",  "id": 193, "lastName": "Stark", "firstName": "Arya", "age": 16 },
    { "status": "Online",  "id": 194, "lastName": "Targaryen", "firstName": "Daenerys", "age": null },
    { "status": "Online",  "id": 195, "lastName": "Melisandre", "firstName": null, "age": 150 },
    { "status": "Online",  "id": 196, "lastName": "Clifford", "firstName": "Ferrara", "age": 44 },
    { "status": "Online",  "id": 197, "lastName": "Frances", "firstName": "Rossini", "age": 36 },
    { "status": "Online",  "id": 198, "lastName": "Roxie", "firstName": "Harvey", "age": 65 },
    { "status": "Online",  "id": 199, "lastName": "Frances", "firstName": "Rossini", "age": 36 },
    { "status": "Online",  "id": 200, "lastName": "Roxie", "firstName": "Harvey", "age": 65 },
    { "status": "Online",  "id": 201, "lastName": "Lannister", "firstName": "Cersei", "age": 42 },
    { "status": "Online",  "id": 202, "lastName": "Lannister", "firstName": "Jaime", "age": 45 },
    { "status": "Online",  "id": 203, "lastName": "Stark", "firstName": "Arya", "age": 16 },
    { "status": "Online",  "id": 204, "lastName": "Targaryen", "firstName": "Daenerys", "age": null },
    { "status": "Online",  "id": 205, "lastName": "Melisandre", "firstName": null, "age": 150 },
    { "status": "Online",  "id": 206, "lastName": "Clifford", "firstName": "Ferrara", "age": 44 },
    { "status": "Online",  "id": 207, "lastName": "Frances", "firstName": "Rossini", "age": 36 },
    { "status": "Online",  "id": 208, "lastName": "Roxie", "firstName": "Harvey", "age": 65 },
    { "status": "Online",  "id": 209, "lastName": "Frances", "firstName": "Rossini", "age": 36 },
    { "status": "Online",  "id": 210, "lastName": "Roxie", "firstName": "Harvey", "age": 65 },
    { "status": "Online",  "id": 211, "lastName": "Lannister", "firstName": "Cersei", "age": 42 },
    { "status": "Online",  "id": 212, "lastName": "Lannister", "firstName": "Jaime", "age": 45 },
    { "status": "Online",  "id": 213, "lastName": "Stark", "firstName": "Arya", "age": 16 },
    { "status": "Online",  "id": 214, "lastName": "Targaryen", "firstName": "Daenerys", "age": null },
    { "status": "Online",  "id": 215, "lastName": "Melisandre", "firstName": null, "age": 150 },
    { "status": "Online",  "id": 216, "lastName": "Clifford", "firstName": "Ferrara", "age": 44 },
    { "status": "Online",  "id": 217, "lastName": "Frances", "firstName": "Rossini", "age": 36 },
    { "status": "Online",  "id": 218, "lastName": "Roxie", "firstName": "Harvey", "age": 65 },
    { "status": "Online",  "id": 219, "lastName": "Frances", "firstName": "Rossini", "age": 36 },
    { "status": "Online",  "id": 220, "lastName": "Roxie", "firstName": "Harvey", "age": 65 },
    { "status": "Online",  "id": 221, "lastName": "Lannister", "firstName": "Cersei", "age": 42 },
    { "status": "Online",  "id": 222, "lastName": "Lannister", "firstName": "Jaime", "age": 45 },
    { "status": "Online",  "id": 223, "lastName": "Stark", "firstName": "Arya", "age": 16 },
    { "status": "Online",  "id": 224, "lastName": "Targaryen", "firstName": "Daenerys", "age": null },
    { "status": "Online",  "id": 225, "lastName": "Melisandre", "firstName": null, "age": 150 },
    { "status": "Online",  "id": 226, "lastName": "Clifford", "firstName": "Ferrara", "age": 44 },
    { "status": "Online",  "id": 227, "lastName": "Frances", "firstName": "Rossini", "age": 36 },
    { "status": "Online",  "id": 228, "lastName": "Roxie", "firstName": "Harvey", "age": 65 },
    { "status": "Online",  "id": 229, "lastName": "Frances", "firstName": "Rossini", "age": 36 },
    { "status": "Online",  "id": 230, "lastName": "Roxie", "firstName": "Harvey", "age": 65 },
    { "status": "Online",  "id": 231, "lastName": "Lannister", "firstName": "Cersei", "age": 42 },
    { "status": "Online",  "id": 232, "lastName": "Lannister", "firstName": "Jaime", "age": 45 },
    { "status": "Online",  "id": 233, "lastName": "Stark", "firstName": "Arya", "age": 16 },
    { "status": "Online",  "id": 234, "lastName": "Targaryen", "firstName": "Daenerys", "age": null },
    { "status": "Online",  "id": 235, "lastName": "Melisandre", "firstName": null, "age": 150 },
    { "status": "Online",  "id": 236, "lastName": "Clifford", "firstName": "Ferrara", "age": 44 },
    { "status": "Online",  "id": 237, "lastName": "Frances", "firstName": "Rossini", "age": 36 },
    { "status": "Online",  "id": 238, "lastName": "Roxie", "firstName": "Harvey", "age": 65 },
    { "status": "Online",  "id": 239, "lastName": "Frances", "firstName": "Rossini", "age": 36 },
    { "status": "Online",  "id": 240, "lastName": "Roxie", "firstName": "Harvey", "age": 65 },
    { "status": "Online",  "id": 241, "lastName": "Lannister", "firstName": "Cersei", "age": 42 },
    { "status": "Online",  "id": 242, "lastName": "Lannister", "firstName": "Jaime", "age": 45 },
    { "status": "Online",  "id": 243, "lastName": "Stark", "firstName": "Arya", "age": 16 },
    { "status": "Online",  "id": 244, "lastName": "Targaryen", "firstName": "Daenerys", "age": null },
    { "status": "Online",  "id": 245, "lastName": "Melisandre", "firstName": null, "age": 150 },
    { "status": "Online",  "id": 246, "lastName": "Clifford", "firstName": "Ferrara", "age": 44 }
  ]
}
